django_tbase_admin-1.1.3.dist-info/licenses/LICENSE
tbase_admin/__init__.py
tbase_admin/admin.py
tbase_admin/apps.py
tbase_admin/custom_admin.py
tbase_admin/models.py
tbase_admin/settings.py
tbase_admin/tests.py
tbase_admin/urls.py
tbase_admin/views.py
tbase_admin/management/__init__.py
tbase_admin/management/commands/__init__.py
tbase_admin/management/commands/clear_hitcount.py
tbase_admin/management/commands/clearhitcount.py
tbase_admin/management/commands/clearsessions.py
tbase_admin/management/commands/tbase_clearhitcount.py
tbase_admin/management/commands/tbase_clearsessions.py
tbase_admin/management/commands/tbase_optimize_tables.py
tbase_admin/migrations/0001_initial.py
tbase_admin/migrations/0002_delete_performancemenuitem.py
tbase_admin/migrations/__init__.py
tbase_admin/static/admin/css/admin.css
tbase_admin/templates/404.html
tbase_admin/templates/500.html
tbase_admin/templates/admin/app_index.html
tbase_admin/templates/admin/base.html
tbase_admin/templates/admin/base_site.html
tbase_admin/templates/admin/login.html
tbase_admin/templates/admin/performance_dashboard.html
django_tbase_admin-1.1.3.dist-info/METADATA
django_tbase_admin-1.1.3.dist-info/WHEEL
django_tbase_admin-1.1.3.dist-info/entry_points.txt
django_tbase_admin-1.1.3.dist-info/top_level.txt
django_tbase_admin-1.1.3.dist-info/RECORD
